py3pin/BookmarkManager.py
py3pin/Pinterest.py
py3pin/Registry.py
py3pin/RequestBuilder.py
py3pin/__init__.py
py3pin/__version__.py
py3_pinterest-1.1.3.dist-info/LICENSE
py3_pinterest-1.1.3.dist-info/METADATA
py3_pinterest-1.1.3.dist-info/WHEEL
py3_pinterest-1.1.3.dist-info/top_level.txt
py3_pinterest-1.1.3.dist-info/RECORD
